networkframe/__init__.py
networkframe/groupby.py
networkframe/networkframe.py
networkframe/types.py
networkframe-0.5.1.dist-info/LICENSE
networkframe-0.5.1.dist-info/METADATA
networkframe-0.5.1.dist-info/WHEEL
networkframe-0.5.1.dist-info/RECORD
