Metadata-Version: 2.1
Name: networkframe
Version: 0.5.1
Summary: Lightweight representations of networks using Pandas DataFrames.
Home-page: https://github.com/bdpedigo/networkframe
License: MIT
Author: Ben Pedigo
Author-email: ben.pedigo@alleninstitute.org
Requires-Python: >=3.11,<3.13
Classifier: Development Status :: 2 - Pre-Alpha
Classifier: Intended Audience :: Developers
Classifier: License :: OSI Approved :: MIT License
Classifier: Natural Language :: English
Classifier: Programming Language :: Python :: 3
Classifier: Programming Language :: Python :: 3.11
Classifier: Programming Language :: Python :: 3.12
Requires-Dist: beartype (>=0.16.4,<0.17.0)
Requires-Dist: networkx (>=2.8.8)
Requires-Dist: pandas (>=2.1.4,<3.0.0)
Requires-Dist: scipy (>=1.11.4,<2.0.0)
Requires-Dist: setuptools (>=69.0.3,<70.0.0)
Requires-Dist: types-setuptools (>=69.0.0.20240115,<70.0.0.0)
